{"name": "Wedding Outcomes"}
{"name": "Step Celebration"}
{"name": "Exceptional Event"}
{"name": "Superb Couture Group"}
{"name": "Maverick Helping Science"}
{"name": "Five Season Blowout"}
{"name": "Sunset Silver Conferences"}
{"name": "Pomp It Mountain"}
{"name": "Party Concourse Charms"}
{"name": "Manage Creative"}
{"name": "Crafty Go F\u00eates"}
{"name": "Occasions Silver Enchantment"}
{"name": "Sage Silver Spring"}
{"name": "The Event Charms"}
{"name": "The Event Now"}
{"name": "Run In Eventertainment"}
{"name": "Heavenly Soiree"}
{"name": "Divine Up Scenes"}
{"name": "InStyle Productions"}
{"name": "Living Red Moment"}
{"name": "Oh How Time Poppers"}
{"name": "Lifetime Jumping Star"}
{"name": "Every The Poppers"}
{"name": "Diamond Red Day"}
{"name": "Show Right Planners"}
{"name": "Realize New Hand"}
{"name": "Original It Parties"}
{"name": "Every Parade Mountain"}
{"name": "Simply Eventments"}
{"name": "Entertainment Socials"}
{"name": "Maverick Style Eventalist"}
{"name": "Little Intercourse Functions"}
{"name": "Manage Main Sweet"}
{"name": "Three Our Collective"}
{"name": "Pomp Ranch"}
{"name": "Duke Good Touch"}
{"name": "Castles Main Design"}
{"name": "Dazzling Gold Fiesta"}
{"name": "Roads Planet"}
{"name": "Blowout Sensations"}
{"name": "Brilliant Gals"}
{"name": "Two By Design"}
{"name": "Paradise Everything"}
{"name": "Jade Concourse Celebration"}
{"name": "Oh How Of Circumstances"}
{"name": "Exceptional Savvy Circumstances"}
{"name": "Party Time Socials"}
{"name": "Ginger Supreme"}
{"name": "X Design"}
{"name": "Exceptional Time Soiree"}
{"name": "Little Happen"}
{"name": "F\u00eate Meetings"}
{"name": "Living Season Coasters"}
{"name": "Carpe Diem Fusion Celebration"}
{"name": "Eventful Time F\u00eates"}
{"name": "Oui Savvy Reasons"}
{"name": "F\u00eate Gold Happen"}
{"name": "Every The Poppers"}
{"name": "Ginger Supreme"}
{"name": "Oui Fiesta"}
{"name": "InStyle Perfect Festivities"}
{"name": "Oui Mania"}
{"name": "Sweet Design"}
{"name": "Amalgamated On The Go"}
{"name": "Every The Poppers"}
{"name": "Organically Red Eventalist"}
{"name": "Duke Good Touch"}
{"name": "Every Helping Soiree"}
{"name": "Viva Night"}
{"name": "Organization Touch"}
{"name": "Every Surge Nirvana"}
{"name": "Enchanting Division"}
{"name": "Celebrate Your Guardians"}
{"name": "Dreams Supreme"}
{"name": "Kudos Right Evermore"}
{"name": "Kaizen Team"}
{"name": "Simply Jumping Delight"}
{"name": "Hella Moments"}
{"name": "Jade Season By Design"}
{"name": "Castles Planning"}
{"name": "Manor Red Savers"}
{"name": "Classy Evermore"}
{"name": "Every Event"}
{"name": "Conference Big Eventualities"}
{"name": "Lively And Supreme"}
{"name": "Platinum Curators"}
{"name": "Eventions Blue Feasts"}
{"name": "Nth Planning Outcomes"}
{"name": "Four Parade Circumstances"}
{"name": "Jade Season By Design"}
{"name": "Fab Your Poppers"}
{"name": "Engaging Nirvana"}
{"name": "Sculpted Savvy Logic"}
{"name": "Spring Now"}
{"name": "Heavenly Soiree"}
{"name": "Sweet Planning"}
{"name": "Oh How Scenarios"}
{"name": "Ovation Entertainment"}
{"name": "Celebration Time Arrangers"}
{"name": "Showtime Blue Celebrations"}
{"name": "Reason Dots"}
